[
  {
    "stage": "posthoc",
    "layer_selection": "all",
    "method": "KMeans",
    "k": 4,
    "warmup_time": 0.0,
    "cluster_time": null,
    "fine_tune_time": 9.019989252090454,
    "measured_inf_time": 0.20816707611083984,
    "estimated_inf_time": 0.18529868125915527,
    "params": 89329,
    "compressed_params_effective": 4821,
    "acc": 1.0,
    "f1": 1.0,
    "recall": 1.0
  },
  {
    "stage": "posthoc",
    "layer_selection": "all",
    "method": "KMeans",
    "k": 8,
    "warmup_time": 0.0,
    "cluster_time": null,
    "fine_tune_time": 9.284783124923706,
    "measured_inf_time": 0.16756319999694824,
    "estimated_inf_time": 0.18529868125915527,
    "params": 89329,
    "compressed_params_effective": 9009,
    "acc": 1.0,
    "f1": 1.0,
    "recall": 1.0
  },
  {
    "stage": "posthoc",
    "layer_selection": "all",
    "method": "KMeans",
    "k": 16,
    "warmup_time": 0.0,
    "cluster_time": null,
    "fine_tune_time": 9.625542402267456,
    "measured_inf_time": 0.14710116386413574,
    "estimated_inf_time": 0.18529868125915527,
    "params": 89329,
    "compressed_params_effective": 16881,
    "acc": 1.0,
    "f1": 1.0,
    "recall": 1.0
  },
  {
    "stage": "posthoc",
    "layer_selection": "all",
    "method": "KMeans",
    "k": 32,
    "warmup_time": 0.0,
    "cluster_time": null,
    "fine_tune_time": 8.769698858261108,
    "measured_inf_time": 0.2414696216583252,
    "estimated_inf_time": 0.18529868125915527,
    "params": 89329,
    "compressed_params_effective": 31985,
    "acc": 1.0,
    "f1": 1.0,
    "recall": 1.0
  },
  {
    "stage": "posthoc",
    "layer_selection": "all",
    "method": "MiniBatchKMeans",
    "k": 4,
    "warmup_time": 0.0,
    "cluster_time": null,
    "fine_tune_time": 9.52837586402893,
    "measured_inf_time": 0.32058119773864746,
    "estimated_inf_time": 0.18529868125915527,
    "params": 89329,
    "compressed_params_effective": 4821,
    "acc": 1.0,
    "f1": 1.0,
    "recall": 1.0
  },
  {
    "stage": "posthoc",
    "layer_selection": "all",
    "method": "MiniBatchKMeans",
    "k": 8,
    "warmup_time": 0.0,
    "cluster_time": null,
    "fine_tune_time": 8.966801881790161,
    "measured_inf_time": 0.23319029808044434,
    "estimated_inf_time": 0.18529868125915527,
    "params": 89329,
    "compressed_params_effective": 9009,
    "acc": 1.0,
    "f1": 1.0,
    "recall": 1.0
  },
  {
    "stage": "posthoc",
    "layer_selection": "all",
    "method": "MiniBatchKMeans",
    "k": 16,
    "warmup_time": 0.0,
    "cluster_time": null,
    "fine_tune_time": 9.051843881607056,
    "measured_inf_time": 0.19484710693359375,
    "estimated_inf_time": 0.18529868125915527,
    "params": 89329,
    "compressed_params_effective": 16881,
    "acc": 1.0,
    "f1": 1.0,
    "recall": 1.0
  },
  {
    "stage": "posthoc",
    "layer_selection": "all",
    "method": "MiniBatchKMeans",
    "k": 32,
    "warmup_time": 0.0,
    "cluster_time": null,
    "fine_tune_time": 9.17984652519226,
    "measured_inf_time": 0.1704246997833252,
    "estimated_inf_time": 0.18529868125915527,
    "params": 89329,
    "compressed_params_effective": 31985,
    "acc": 1.0,
    "f1": 1.0,
    "recall": 1.0
  },
  {
    "stage": "posthoc",
    "layer_selection": "all",
    "method": "EFDPC",
    "k": 4,
    "warmup_time": 0.0,
    "cluster_time": null,
    "fine_tune_time": 10.022263050079346,
    "measured_inf_time": 0.201141357421875,
    "estimated_inf_time": 0.18529868125915527,
    "params": 89329,
    "compressed_params_effective": 4821,
    "acc": 1.0,
    "f1": 1.0,
    "recall": 1.0
  },
  {
    "stage": "posthoc",
    "layer_selection": "all",
    "method": "EFDPC",
    "k": 8,
    "warmup_time": 0.0,
    "cluster_time": null,
    "fine_tune_time": 8.815971612930298,
    "measured_inf_time": 0.1913297176361084,
    "estimated_inf_time": 0.18529868125915527,
    "params": 89329,
    "compressed_params_effective": 9009,
    "acc": 1.0,
    "f1": 1.0,
    "recall": 1.0
  },
  {
    "stage": "posthoc",
    "layer_selection": "all",
    "method": "EFDPC",
    "k": 16,
    "warmup_time": 0.0,
    "cluster_time": null,
    "fine_tune_time": 9.07264518737793,
    "measured_inf_time": 0.16866564750671387,
    "estimated_inf_time": 0.18529868125915527,
    "params": 89329,
    "compressed_params_effective": 16881,
    "acc": 1.0,
    "f1": 1.0,
    "recall": 1.0
  },
  {
    "stage": "posthoc",
    "layer_selection": "all",
    "method": "EFDPC",
    "k": 32,
    "warmup_time": 0.0,
    "cluster_time": null,
    "fine_tune_time": 9.302825927734375,
    "measured_inf_time": 0.15571379661560059,
    "estimated_inf_time": 0.18529868125915527,
    "params": 89329,
    "compressed_params_effective": 31985,
    "acc": 1.0,
    "f1": 1.0,
    "recall": 1.0
  },
  {
    "stage": "posthoc",
    "layer_selection": "exclude_first_last",
    "method": "KMeans",
    "k": 4,
    "warmup_time": 0.0,
    "cluster_time": null,
    "fine_tune_time": 9.150044679641724,
    "measured_inf_time": 0.19169139862060547,
    "estimated_inf_time": 0.18529868125915527,
    "params": 89329,
    "compressed_params_effective": 5073,
    "acc": 1.0,
    "f1": 1.0,
    "recall": 1.0
  },
  {
    "stage": "posthoc",
    "layer_selection": "exclude_first_last",
    "method": "KMeans",
    "k": 8,
    "warmup_time": 0.0,
    "cluster_time": null,
    "fine_tune_time": 9.28242540359497,
    "measured_inf_time": 0.21784639358520508,
    "estimated_inf_time": 0.18529868125915527,
    "params": 89329,
    "compressed_params_effective": 9009,
    "acc": 1.0,
    "f1": 1.0,
    "recall": 1.0
  },
  {
    "stage": "posthoc",
    "layer_selection": "exclude_first_last",
    "method": "KMeans",
    "k": 16,
    "warmup_time": 0.0,
    "cluster_time": null,
    "fine_tune_time": 8.82123351097107,
    "measured_inf_time": 0.13876080513000488,
    "estimated_inf_time": 0.18529868125915527,
    "params": 89329,
    "compressed_params_effective": 16881,
    "acc": 1.0,
    "f1": 1.0,
    "recall": 1.0
  },
  {
    "stage": "posthoc",
    "layer_selection": "exclude_first_last",
    "method": "KMeans",
    "k": 32,
    "warmup_time": 0.0,
    "cluster_time": null,
    "fine_tune_time": 8.545811176300049,
    "measured_inf_time": 0.14734888076782227,
    "estimated_inf_time": 0.18529868125915527,
    "params": 89329,
    "compressed_params_effective": 31985,
    "acc": 1.0,
    "f1": 1.0,
    "recall": 1.0
  },
  {
    "stage": "posthoc",
    "layer_selection": "exclude_first_last",
    "method": "MiniBatchKMeans",
    "k": 4,
    "warmup_time": 0.0,
    "cluster_time": null,
    "fine_tune_time": 9.92301630973816,
    "measured_inf_time": 0.2272489070892334,
    "estimated_inf_time": 0.18529868125915527,
    "params": 89329,
    "compressed_params_effective": 5073,
    "acc": 1.0,
    "f1": 1.0,
    "recall": 1.0
  },
  {
    "stage": "posthoc",
    "layer_selection": "exclude_first_last",
    "method": "MiniBatchKMeans",
    "k": 8,
    "warmup_time": 0.0,
    "cluster_time": null,
    "fine_tune_time": 11.089063882827759,
    "measured_inf_time": 0.19627690315246582,
    "estimated_inf_time": 0.18529868125915527,
    "params": 89329,
    "compressed_params_effective": 9009,
    "acc": 1.0,
    "f1": 1.0,
    "recall": 1.0
  },
  {
    "stage": "posthoc",
    "layer_selection": "exclude_first_last",
    "method": "MiniBatchKMeans",
    "k": 16,
    "warmup_time": 0.0,
    "cluster_time": null,
    "fine_tune_time": 9.998925685882568,
    "measured_inf_time": 0.17454814910888672,
    "estimated_inf_time": 0.18529868125915527,
    "params": 89329,
    "compressed_params_effective": 16881,
    "acc": 1.0,
    "f1": 1.0,
    "recall": 1.0
  },
  {
    "stage": "posthoc",
    "layer_selection": "exclude_first_last",
    "method": "MiniBatchKMeans",
    "k": 32,
    "warmup_time": 0.0,
    "cluster_time": null,
    "fine_tune_time": 9.645133256912231,
    "measured_inf_time": 0.16668939590454102,
    "estimated_inf_time": 0.18529868125915527,
    "params": 89329,
    "compressed_params_effective": 31985,
    "acc": 1.0,
    "f1": 1.0,
    "recall": 1.0
  },
  {
    "stage": "posthoc",
    "layer_selection": "exclude_first_last",
    "method": "EFDPC",
    "k": 4,
    "warmup_time": 0.0,
    "cluster_time": null,
    "fine_tune_time": 11.236532211303711,
    "measured_inf_time": 0.2383270263671875,
    "estimated_inf_time": 0.18529868125915527,
    "params": 89329,
    "compressed_params_effective": 5073,
    "acc": 1.0,
    "f1": 1.0,
    "recall": 1.0
  },
  {
    "stage": "posthoc",
    "layer_selection": "exclude_first_last",
    "method": "EFDPC",
    "k": 8,
    "warmup_time": 0.0,
    "cluster_time": null,
    "fine_tune_time": 11.790420770645142,
    "measured_inf_time": 0.26247501373291016,
    "estimated_inf_time": 0.18529868125915527,
    "params": 89329,
    "compressed_params_effective": 9009,
    "acc": 1.0,
    "f1": 1.0,
    "recall": 1.0
  },
  {
    "stage": "posthoc",
    "layer_selection": "exclude_first_last",
    "method": "EFDPC",
    "k": 16,
    "warmup_time": 0.0,
    "cluster_time": null,
    "fine_tune_time": 15.22594952583313,
    "measured_inf_time": 0.2627403736114502,
    "estimated_inf_time": 0.18529868125915527,
    "params": 89329,
    "compressed_params_effective": 16881,
    "acc": 1.0,
    "f1": 1.0,
    "recall": 1.0
  },
  {
    "stage": "posthoc",
    "layer_selection": "exclude_first_last",
    "method": "EFDPC",
    "k": 32,
    "warmup_time": 0.0,
    "cluster_time": null,
    "fine_tune_time": 11.123642921447754,
    "measured_inf_time": 0.2010035514831543,
    "estimated_inf_time": 0.18529868125915527,
    "params": 89329,
    "compressed_params_effective": 31985,
    "acc": 1.0,
    "f1": 1.0,
    "recall": 1.0
  },
  {
    "stage": "partial",
    "layer_selection": "all",
    "method": "KMeans",
    "k": 4,
    "warmup_time": 5.1816322803497314,
    "cluster_time": null,
    "fine_tune_time": 12.509926795959473,
    "measured_inf_time": 0.20351767539978027,
    "estimated_inf_time": 0.18529868125915527,
    "params": 89329,
    "compressed_params_effective": 4821,
    "acc": 1.0,
    "f1": 1.0,
    "recall": 1.0
  },
  {
    "stage": "partial",
    "layer_selection": "all",
    "method": "KMeans",
    "k": 8,
    "warmup_time": 4.230214357376099,
    "cluster_time": null,
    "fine_tune_time": 16.00528335571289,
    "measured_inf_time": 0.25266289710998535,
    "estimated_inf_time": 0.18529868125915527,
    "params": 89329,
    "compressed_params_effective": 9009,
    "acc": 1.0,
    "f1": 1.0,
    "recall": 1.0
  },
  {
    "stage": "partial",
    "layer_selection": "all",
    "method": "KMeans",
    "k": 16,
    "warmup_time": 7.162170886993408,
    "cluster_time": null,
    "fine_tune_time": 12.763495922088623,
    "measured_inf_time": 0.22475600242614746,
    "estimated_inf_time": 0.18529868125915527,
    "params": 89329,
    "compressed_params_effective": 16881,
    "acc": 1.0,
    "f1": 1.0,
    "recall": 1.0
  },
  {
    "stage": "partial",
    "layer_selection": "all",
    "method": "KMeans",
    "k": 32,
    "warmup_time": 5.4709484577178955,
    "cluster_time": null,
    "fine_tune_time": 17.0859215259552,
    "measured_inf_time": 0.4058825969696045,
    "estimated_inf_time": 0.18529868125915527,
    "params": 89329,
    "compressed_params_effective": 31985,
    "acc": 1.0,
    "f1": 1.0,
    "recall": 1.0
  },
  {
    "stage": "partial",
    "layer_selection": "all",
    "method": "MiniBatchKMeans",
    "k": 4,
    "warmup_time": 6.356741905212402,
    "cluster_time": null,
    "fine_tune_time": 12.39607572555542,
    "measured_inf_time": 0.2172558307647705,
    "estimated_inf_time": 0.18529868125915527,
    "params": 89329,
    "compressed_params_effective": 4821,
    "acc": 1.0,
    "f1": 1.0,
    "recall": 1.0
  },
  {
    "stage": "partial",
    "layer_selection": "all",
    "method": "MiniBatchKMeans",
    "k": 8,
    "warmup_time": 4.033350944519043,
    "cluster_time": null,
    "fine_tune_time": 10.159418106079102,
    "measured_inf_time": 0.19839167594909668,
    "estimated_inf_time": 0.18529868125915527,
    "params": 89329,
    "compressed_params_effective": 9009,
    "acc": 1.0,
    "f1": 1.0,
    "recall": 1.0
  },
  {
    "stage": "partial",
    "layer_selection": "all",
    "method": "MiniBatchKMeans",
    "k": 16,
    "warmup_time": 3.5013349056243896,
    "cluster_time": null,
    "fine_tune_time": 9.694148778915405,
    "measured_inf_time": 0.22490262985229492,
    "estimated_inf_time": 0.18529868125915527,
    "params": 89329,
    "compressed_params_effective": 16881,
    "acc": 1.0,
    "f1": 1.0,
    "recall": 1.0
  },
  {
    "stage": "partial",
    "layer_selection": "all",
    "method": "MiniBatchKMeans",
    "k": 32,
    "warmup_time": 4.059921503067017,
    "cluster_time": null,
    "fine_tune_time": 9.778455018997192,
    "measured_inf_time": 0.1356031894683838,
    "estimated_inf_time": 0.18529868125915527,
    "params": 89329,
    "compressed_params_effective": 31985,
    "acc": 1.0,
    "f1": 1.0,
    "recall": 1.0
  },
  {
    "stage": "partial",
    "layer_selection": "all",
    "method": "EFDPC",
    "k": 4,
    "warmup_time": 3.7942569255828857,
    "cluster_time": null,
    "fine_tune_time": 9.825425148010254,
    "measured_inf_time": 0.17168092727661133,
    "estimated_inf_time": 0.18529868125915527,
    "params": 89329,
    "compressed_params_effective": 4821,
    "acc": 1.0,
    "f1": 1.0,
    "recall": 1.0
  },
  {
    "stage": "partial",
    "layer_selection": "all",
    "method": "EFDPC",
    "k": 8,
    "warmup_time": 3.8405399322509766,
    "cluster_time": null,
    "fine_tune_time": 9.540408849716187,
    "measured_inf_time": 0.12618422508239746,
    "estimated_inf_time": 0.18529868125915527,
    "params": 89329,
    "compressed_params_effective": 9009,
    "acc": 1.0,
    "f1": 1.0,
    "recall": 1.0
  },
  {
    "stage": "partial",
    "layer_selection": "all",
    "method": "EFDPC",
    "k": 16,
    "warmup_time": 3.7846648693084717,
    "cluster_time": null,
    "fine_tune_time": 9.148026466369629,
    "measured_inf_time": 0.20689845085144043,
    "estimated_inf_time": 0.18529868125915527,
    "params": 89329,
    "compressed_params_effective": 16881,
    "acc": 1.0,
    "f1": 1.0,
    "recall": 1.0
  },
  {
    "stage": "partial",
    "layer_selection": "all",
    "method": "EFDPC",
    "k": 32,
    "warmup_time": 3.781494379043579,
    "cluster_time": null,
    "fine_tune_time": 9.746102333068848,
    "measured_inf_time": 0.2520112991333008,
    "estimated_inf_time": 0.18529868125915527,
    "params": 89329,
    "compressed_params_effective": 31985,
    "acc": 1.0,
    "f1": 1.0,
    "recall": 1.0
  },
  {
    "stage": "partial",
    "layer_selection": "exclude_first_last",
    "method": "KMeans",
    "k": 4,
    "warmup_time": 3.8340930938720703,
    "cluster_time": null,
    "fine_tune_time": 9.632683992385864,
    "measured_inf_time": 0.1448378562927246,
    "estimated_inf_time": 0.18529868125915527,
    "params": 89329,
    "compressed_params_effective": 5073,
    "acc": 1.0,
    "f1": 1.0,
    "recall": 1.0
  },
  {
    "stage": "partial",
    "layer_selection": "exclude_first_last",
    "method": "KMeans",
    "k": 8,
    "warmup_time": 3.9087324142456055,
    "cluster_time": null,
    "fine_tune_time": 9.434180498123169,
    "measured_inf_time": 0.17994070053100586,
    "estimated_inf_time": 0.18529868125915527,
    "params": 89329,
    "compressed_params_effective": 9009,
    "acc": 1.0,
    "f1": 1.0,
    "recall": 1.0
  },
  {
    "stage": "partial",
    "layer_selection": "exclude_first_last",
    "method": "KMeans",
    "k": 16,
    "warmup_time": 3.88110089302063,
    "cluster_time": null,
    "fine_tune_time": 10.310965061187744,
    "measured_inf_time": 0.2404003143310547,
    "estimated_inf_time": 0.18529868125915527,
    "params": 89329,
    "compressed_params_effective": 16881,
    "acc": 1.0,
    "f1": 1.0,
    "recall": 1.0
  },
  {
    "stage": "partial",
    "layer_selection": "exclude_first_last",
    "method": "KMeans",
    "k": 32,
    "warmup_time": 3.6627705097198486,
    "cluster_time": null,
    "fine_tune_time": 9.302357912063599,
    "measured_inf_time": 0.24139022827148438,
    "estimated_inf_time": 0.18529868125915527,
    "params": 89329,
    "compressed_params_effective": 31985,
    "acc": 1.0,
    "f1": 1.0,
    "recall": 1.0
  },
  {
    "stage": "partial",
    "layer_selection": "exclude_first_last",
    "method": "MiniBatchKMeans",
    "k": 4,
    "warmup_time": 4.033981561660767,
    "cluster_time": null,
    "fine_tune_time": 9.549457788467407,
    "measured_inf_time": 0.16703581809997559,
    "estimated_inf_time": 0.18529868125915527,
    "params": 89329,
    "compressed_params_effective": 5073,
    "acc": 1.0,
    "f1": 1.0,
    "recall": 1.0
  },
  {
    "stage": "partial",
    "layer_selection": "exclude_first_last",
    "method": "MiniBatchKMeans",
    "k": 8,
    "warmup_time": 3.840348243713379,
    "cluster_time": null,
    "fine_tune_time": 9.707650184631348,
    "measured_inf_time": 0.18498969078063965,
    "estimated_inf_time": 0.18529868125915527,
    "params": 89329,
    "compressed_params_effective": 9009,
    "acc": 1.0,
    "f1": 1.0,
    "recall": 1.0
  },
  {
    "stage": "partial",
    "layer_selection": "exclude_first_last",
    "method": "MiniBatchKMeans",
    "k": 16,
    "warmup_time": 3.891615152359009,
    "cluster_time": null,
    "fine_tune_time": 9.651678323745728,
    "measured_inf_time": 0.1542799472808838,
    "estimated_inf_time": 0.18529868125915527,
    "params": 89329,
    "compressed_params_effective": 16881,
    "acc": 1.0,
    "f1": 1.0,
    "recall": 1.0
  },
  {
    "stage": "partial",
    "layer_selection": "exclude_first_last",
    "method": "MiniBatchKMeans",
    "k": 32,
    "warmup_time": 3.76589298248291,
    "cluster_time": null,
    "fine_tune_time": 8.90910816192627,
    "measured_inf_time": 0.1925041675567627,
    "estimated_inf_time": 0.18529868125915527,
    "params": 89329,
    "compressed_params_effective": 31985,
    "acc": 1.0,
    "f1": 1.0,
    "recall": 1.0
  },
  {
    "stage": "partial",
    "layer_selection": "exclude_first_last",
    "method": "EFDPC",
    "k": 4,
    "warmup_time": 3.688317060470581,
    "cluster_time": null,
    "fine_tune_time": 9.27058744430542,
    "measured_inf_time": 0.1934216022491455,
    "estimated_inf_time": 0.18529868125915527,
    "params": 89329,
    "compressed_params_effective": 5073,
    "acc": 1.0,
    "f1": 1.0,
    "recall": 1.0
  },
  {
    "stage": "partial",
    "layer_selection": "exclude_first_last",
    "method": "EFDPC",
    "k": 8,
    "warmup_time": 3.605694055557251,
    "cluster_time": null,
    "fine_tune_time": 9.588377475738525,
    "measured_inf_time": 0.20886492729187012,
    "estimated_inf_time": 0.18529868125915527,
    "params": 89329,
    "compressed_params_effective": 9009,
    "acc": 1.0,
    "f1": 1.0,
    "recall": 1.0
  },
  {
    "stage": "partial",
    "layer_selection": "exclude_first_last",
    "method": "EFDPC",
    "k": 16,
    "warmup_time": 3.9318010807037354,
    "cluster_time": null,
    "fine_tune_time": 8.975722074508667,
    "measured_inf_time": 0.14983701705932617,
    "estimated_inf_time": 0.18529868125915527,
    "params": 89329,
    "compressed_params_effective": 16881,
    "acc": 1.0,
    "f1": 1.0,
    "recall": 1.0
  },
  {
    "stage": "partial",
    "layer_selection": "exclude_first_last",
    "method": "EFDPC",
    "k": 32,
    "warmup_time": 3.6694302558898926,
    "cluster_time": null,
    "fine_tune_time": 9.329058647155762,
    "measured_inf_time": 0.1498875617980957,
    "estimated_inf_time": 0.18529868125915527,
    "params": 89329,
    "compressed_params_effective": 31985,
    "acc": 1.0,
    "f1": 1.0,
    "recall": 1.0
  }
]